devdeck_core/__init__.py
devdeck_core/control_context.py
devdeck_core/deck_context.py
devdeck_core/image_processing.py
devdeck_core/mock_deck_context.py
devdeck_core/renderer.py
devdeck_core/assets/Roboto License.txt
devdeck_core/assets/Roboto-Regular.ttf
devdeck_core/controls/__init__.py
devdeck_core/controls/deck_control.py
devdeck_core/decks/__init__.py
devdeck_core/decks/deck_controller.py
devdeck_core/rendering/__init__.py
devdeck_core/rendering/badge_count_renderer.py
devdeck_core/rendering/emoji_renderer.py
devdeck_core/rendering/image_renderer.py
devdeck_core/rendering/text_renderer.py
devdeck_core/settings/__init__.py
devdeck_core/settings/cerberus_utils.py
devdeck_core/settings/control_validation_error.py
tests/__init__.py
tests/devdeck/__init__.py
tests/devdeck/core/__init__.py
tests/devdeck/core/settings/__init__.py
tests/devdeck/core/settings/test_control_validation_error.py
devdeck_core-1.0.8.dist-info/LICENSE
devdeck_core-1.0.8.dist-info/METADATA
devdeck_core-1.0.8.dist-info/WHEEL
devdeck_core-1.0.8.dist-info/top_level.txt
devdeck_core-1.0.8.dist-info/RECORD
