Metadata-Version: 2.1
Name: devdeck_core
Version: 1.0.8
Summary: A developer's approach to using a Stream Deck.
Home-page: https://github.com/jamesridgway/devdeck_core
Author: James Ridgway
License: MIT
License-File: LICENSE
Requires-Dist: assertpy
Requires-Dist: cerberus
Requires-Dist: pillow
Requires-Dist: pytest
Requires-Dist: requests
Requires-Dist: streamdeck
